uagent_a2a_adapter/__init__.py
uagent_a2a_adapter/adapter.py
uagent_a2a_adapter/py.typed
uagent_a2a_adapter-0.1.5.dist-info/METADATA
uagent_a2a_adapter-0.1.5.dist-info/WHEEL
uagent_a2a_adapter-0.1.5.dist-info/top_level.txt
uagent_a2a_adapter-0.1.5.dist-info/RECORD
